LICENSE
MANIFEST.in
README.md
setup.py
bits/__init__.py
bits/cache.py
bits/currency.py
bits/general.py
bits/gis.py
bits/html5.py
bits/http.py
bits/models.py
bits/management/__init__.py
bits/management/commands/__init__.py
bits/management/commands/after_syncdb.py
bits/management/commands/clear_cache.py
bits/templatetags/__init__.py
bits/templatetags/attribute.py
bits/templatetags/currency.py
bits/templatetags/custom_utils.py
django_bits.egg-info/PKG-INFO
django_bits.egg-info/SOURCES.txt
django_bits.egg-info/dependency_links.txt
django_bits.egg-info/top_level.txt