Metadata-Version: 1.1
Name: django-bits
Version: 0.3
Summary: Basic utilities and helpers for django projects
Home-page: http://github.com/scdoshi/django-bits/
Author: Siddharth Doshi
Author-email: scdoshi@gmail.com
License: Simplified BSD
Platform: UNKNOWN
Classifier: Development Status :: 4 - Beta
Classifier: Environment :: Web Environment
Classifier: Framework :: Django
Classifier: Intended Audience :: Developers
Classifier: License :: OSI Approved :: BSD License
Classifier: Operating System :: OS Independent
Classifier: Programming Language :: Python
Classifier: Topic :: Software Development :: Libraries :: Python Modules
